TCVB_calc/__init__.py
TCVB_calc/calc_main.py
tests/__init__.py
tests/test_add.py
tests/test_divide.py
tests/test_multiply.py
tests/test_nroot.py
tests/test_reset.py
tests/test_subtract.py
TCVB_calc-0.1.0.dist-info/LICENSE
TCVB_calc-0.1.0.dist-info/METADATA
TCVB_calc-0.1.0.dist-info/WHEEL
TCVB_calc-0.1.0.dist-info/top_level.txt
TCVB_calc-0.1.0.dist-info/RECORD
