Metadata-Version: 2.1
Name: TCVB-calc
Version: 0.1.0
Summary: For performing simple mathematical calculations
Home-page: https://github.com/TuringCollegeSubmissions/vbeino-DWWP.1
Author: Vytautas Beinoravicius
Author-email: vytasbein@gmail.com
Classifier: Programming Language :: Python :: 3
Classifier: License :: OSI Approved :: MIT License
Classifier: Operating System :: OS Independent
Requires-Python: >=3.6
License-File: LICENSE
